{
  "type": "File",
  "start": 0,
  "end": 299,
  "loc": {
    "start": {
      "line": 1,
      "column": 0
    },
    "end": {
      "line": 10,
      "column": 84
    }
  },
  "program": {
    "type": "Program",
    "start": 0,
    "end": 299,
    "loc": {
      "start": {
        "line": 1,
        "column": 0
      },
      "end": {
        "line": 10,
        "column": 84
      }
    },
    "sourceType": "module",
    "body": [
      {
        "type": "VariableDeclaration",
        "start": 0,
        "end": 35,
        "loc": {
          "start": {
            "line": 1,
            "column": 0
          },
          "end": {
            "line": 1,
            "column": 35
          }
        },
        "declarations": [
          {
            "type": "VariableDeclarator",
            "start": 4,
            "end": 34,
            "loc": {
              "start": {
                "line": 1,
                "column": 4
              },
              "end": {
                "line": 1,
                "column": 34
              }
            },
            "id": {
              "type": "Identifier",
              "start": 4,
              "end": 12,
              "loc": {
                "start": {
                  "line": 1,
                  "column": 4
                },
                "end": {
                  "line": 1,
                  "column": 12
                },
                "identifierName": "mongoose"
              },
              "name": "mongoose"
            },
            "init": {
              "type": "CallExpression",
              "start": 15,
              "end": 34,
              "loc": {
                "start": {
                  "line": 1,
                  "column": 15
                },
                "end": {
                  "line": 1,
                  "column": 34
                }
              },
              "callee": {
                "type": "Identifier",
                "start": 15,
                "end": 22,
                "loc": {
                  "start": {
                    "line": 1,
                    "column": 15
                  },
                  "end": {
                    "line": 1,
                    "column": 22
                  },
                  "identifierName": "require"
                },
                "name": "require"
              },
              "arguments": [
                {
                  "type": "StringLiteral",
                  "start": 23,
                  "end": 33,
                  "loc": {
                    "start": {
                      "line": 1,
                      "column": 23
                    },
                    "end": {
                      "line": 1,
                      "column": 33
                    }
                  },
                  "extra": {
                    "rawValue": "mongoose",
                    "raw": "'mongoose'"
                  },
                  "value": "mongoose"
                }
              ]
            }
          }
        ],
        "kind": "var"
      },
      {
        "type": "VariableDeclaration",
        "start": 39,
        "end": 211,
        "loc": {
          "start": {
            "line": 3,
            "column": 0
          },
          "end": {
            "line": 8,
            "column": 23
          }
        },
        "declarations": [
          {
            "type": "VariableDeclarator",
            "start": 43,
            "end": 210,
            "loc": {
              "start": {
                "line": 3,
                "column": 4
              },
              "end": {
                "line": 8,
                "column": 22
              }
            },
            "id": {
              "type": "Identifier",
              "start": 43,
              "end": 61,
              "loc": {
                "start": {
                  "line": 3,
                  "column": 4
                },
                "end": {
                  "line": 3,
                  "column": 22
                },
                "identifierName": "EntradaSaidaSchema"
              },
              "name": "EntradaSaidaSchema"
            },
            "init": {
              "type": "NewExpression",
              "start": 64,
              "end": 210,
              "loc": {
                "start": {
                  "line": 3,
                  "column": 25
                },
                "end": {
                  "line": 8,
                  "column": 22
                }
              },
              "callee": {
                "type": "MemberExpression",
                "start": 68,
                "end": 83,
                "loc": {
                  "start": {
                    "line": 3,
                    "column": 29
                  },
                  "end": {
                    "line": 3,
                    "column": 44
                  }
                },
                "object": {
                  "type": "Identifier",
                  "start": 68,
                  "end": 76,
                  "loc": {
                    "start": {
                      "line": 3,
                      "column": 29
                    },
                    "end": {
                      "line": 3,
                      "column": 37
                    },
                    "identifierName": "mongoose"
                  },
                  "name": "mongoose"
                },
                "property": {
                  "type": "Identifier",
                  "start": 77,
                  "end": 83,
                  "loc": {
                    "start": {
                      "line": 3,
                      "column": 38
                    },
                    "end": {
                      "line": 3,
                      "column": 44
                    },
                    "identifierName": "Schema"
                  },
                  "name": "Schema"
                },
                "computed": false
              },
              "arguments": [
                {
                  "type": "ObjectExpression",
                  "start": 84,
                  "end": 189,
                  "loc": {
                    "start": {
                      "line": 3,
                      "column": 45
                    },
                    "end": {
                      "line": 8,
                      "column": 1
                    }
                  },
                  "properties": [
                    {
                      "type": "ObjectProperty",
                      "start": 113,
                      "end": 132,
                      "loc": {
                        "start": {
                          "line": 5,
                          "column": 2
                        },
                        "end": {
                          "line": 5,
                          "column": 21
                        }
                      },
                      "method": false,
                      "shorthand": false,
                      "computed": false,
                      "key": {
                        "type": "Identifier",
                        "start": 113,
                        "end": 118,
                        "loc": {
                          "start": {
                            "line": 5,
                            "column": 2
                          },
                          "end": {
                            "line": 5,
                            "column": 7
                          },
                          "identifierName": "_Nome"
                        },
                        "name": "_Nome",
                        "leadingComments": null
                      },
                      "value": {
                        "type": "ObjectExpression",
                        "start": 119,
                        "end": 132,
                        "loc": {
                          "start": {
                            "line": 5,
                            "column": 8
                          },
                          "end": {
                            "line": 5,
                            "column": 21
                          }
                        },
                        "properties": [
                          {
                            "type": "ObjectProperty",
                            "start": 120,
                            "end": 131,
                            "loc": {
                              "start": {
                                "line": 5,
                                "column": 9
                              },
                              "end": {
                                "line": 5,
                                "column": 20
                              }
                            },
                            "method": false,
                            "shorthand": false,
                            "computed": false,
                            "key": {
                              "type": "Identifier",
                              "start": 120,
                              "end": 124,
                              "loc": {
                                "start": {
                                  "line": 5,
                                  "column": 9
                                },
                                "end": {
                                  "line": 5,
                                  "column": 13
                                },
                                "identifierName": "type"
                              },
                              "name": "type"
                            },
                            "value": {
                              "type": "Identifier",
                              "start": 125,
                              "end": 131,
                              "loc": {
                                "start": {
                                  "line": 5,
                                  "column": 14
                                },
                                "end": {
                                  "line": 5,
                                  "column": 20
                                },
                                "identifierName": "String"
                              },
                              "name": "String"
                            }
                          }
                        ]
                      },
                      "leadingComments": [
                        {
                          "type": "CommentLine",
                          "value": "_id:{type:String},",
                          "start": 89,
                          "end": 109,
                          "loc": {
                            "start": {
                              "line": 4,
                              "column": 2
                            },
                            "end": {
                              "line": 4,
                              "column": 22
                            }
                          }
                        }
                      ]
                    },
                    {
                      "type": "ObjectProperty",
                      "start": 137,
                      "end": 164,
                      "loc": {
                        "start": {
                          "line": 6,
                          "column": 2
                        },
                        "end": {
                          "line": 6,
                          "column": 29
                        }
                      },
                      "method": false,
                      "shorthand": false,
                      "computed": false,
                      "key": {
                        "type": "Identifier",
                        "start": 137,
                        "end": 150,
                        "loc": {
                          "start": {
                            "line": 6,
                            "column": 2
                          },
                          "end": {
                            "line": 6,
                            "column": 15
                          },
                          "identifierName": "_EntradaSaida"
                        },
                        "name": "_EntradaSaida"
                      },
                      "value": {
                        "type": "ObjectExpression",
                        "start": 151,
                        "end": 164,
                        "loc": {
                          "start": {
                            "line": 6,
                            "column": 16
                          },
                          "end": {
                            "line": 6,
                            "column": 29
                          }
                        },
                        "properties": [
                          {
                            "type": "ObjectProperty",
                            "start": 152,
                            "end": 163,
                            "loc": {
                              "start": {
                                "line": 6,
                                "column": 17
                              },
                              "end": {
                                "line": 6,
                                "column": 28
                              }
                            },
                            "method": false,
                            "shorthand": false,
                            "computed": false,
                            "key": {
                              "type": "Identifier",
                              "start": 152,
                              "end": 156,
                              "loc": {
                                "start": {
                                  "line": 6,
                                  "column": 17
                                },
                                "end": {
                                  "line": 6,
                                  "column": 21
                                },
                                "identifierName": "type"
                              },
                              "name": "type"
                            },
                            "value": {
                              "type": "Identifier",
                              "start": 157,
                              "end": 163,
                              "loc": {
                                "start": {
                                  "line": 6,
                                  "column": 22
                                },
                                "end": {
                                  "line": 6,
                                  "column": 28
                                },
                                "identifierName": "String"
                              },
                              "name": "String"
                            }
                          }
                        ]
                      }
                    },
                    {
                      "type": "ObjectProperty",
                      "start": 169,
                      "end": 186,
                      "loc": {
                        "start": {
                          "line": 7,
                          "column": 2
                        },
                        "end": {
                          "line": 7,
                          "column": 19
                        }
                      },
                      "method": false,
                      "shorthand": false,
                      "computed": false,
                      "key": {
                        "type": "Identifier",
                        "start": 169,
                        "end": 174,
                        "loc": {
                          "start": {
                            "line": 7,
                            "column": 2
                          },
                          "end": {
                            "line": 7,
                            "column": 7
                          },
                          "identifierName": "_Hora"
                        },
                        "name": "_Hora"
                      },
                      "value": {
                        "type": "ObjectExpression",
                        "start": 175,
                        "end": 186,
                        "loc": {
                          "start": {
                            "line": 7,
                            "column": 8
                          },
                          "end": {
                            "line": 7,
                            "column": 19
                          }
                        },
                        "properties": [
                          {
                            "type": "ObjectProperty",
                            "start": 176,
                            "end": 185,
                            "loc": {
                              "start": {
                                "line": 7,
                                "column": 9
                              },
                              "end": {
                                "line": 7,
                                "column": 18
                              }
                            },
                            "method": false,
                            "shorthand": false,
                            "computed": false,
                            "key": {
                              "type": "Identifier",
                              "start": 176,
                              "end": 180,
                              "loc": {
                                "start": {
                                  "line": 7,
                                  "column": 9
                                },
                                "end": {
                                  "line": 7,
                                  "column": 13
                                },
                                "identifierName": "type"
                              },
                              "name": "type"
                            },
                            "value": {
                              "type": "Identifier",
                              "start": 181,
                              "end": 185,
                              "loc": {
                                "start": {
                                  "line": 7,
                                  "column": 14
                                },
                                "end": {
                                  "line": 7,
                                  "column": 18
                                },
                                "identifierName": "Date"
                              },
                              "name": "Date"
                            }
                          }
                        ]
                      }
                    }
                  ]
                },
                {
                  "type": "ObjectExpression",
                  "start": 191,
                  "end": 209,
                  "loc": {
                    "start": {
                      "line": 8,
                      "column": 3
                    },
                    "end": {
                      "line": 8,
                      "column": 21
                    }
                  },
                  "properties": [
                    {
                      "type": "ObjectProperty",
                      "start": 192,
                      "end": 208,
                      "loc": {
                        "start": {
                          "line": 8,
                          "column": 4
                        },
                        "end": {
                          "line": 8,
                          "column": 20
                        }
                      },
                      "method": false,
                      "shorthand": false,
                      "computed": false,
                      "key": {
                        "type": "Identifier",
                        "start": 192,
                        "end": 202,
                        "loc": {
                          "start": {
                            "line": 8,
                            "column": 4
                          },
                          "end": {
                            "line": 8,
                            "column": 14
                          },
                          "identifierName": "timestamps"
                        },
                        "name": "timestamps"
                      },
                      "value": {
                        "type": "BooleanLiteral",
                        "start": 204,
                        "end": 208,
                        "loc": {
                          "start": {
                            "line": 8,
                            "column": 16
                          },
                          "end": {
                            "line": 8,
                            "column": 20
                          }
                        },
                        "value": true
                      }
                    }
                  ]
                }
              ]
            }
          }
        ],
        "kind": "var"
      },
      {
        "type": "ExpressionStatement",
        "start": 215,
        "end": 299,
        "loc": {
          "start": {
            "line": 10,
            "column": 0
          },
          "end": {
            "line": 10,
            "column": 84
          }
        },
        "expression": {
          "type": "AssignmentExpression",
          "start": 215,
          "end": 298,
          "loc": {
            "start": {
              "line": 10,
              "column": 0
            },
            "end": {
              "line": 10,
              "column": 83
            }
          },
          "operator": "=",
          "left": {
            "type": "MemberExpression",
            "start": 215,
            "end": 229,
            "loc": {
              "start": {
                "line": 10,
                "column": 0
              },
              "end": {
                "line": 10,
                "column": 14
              }
            },
            "object": {
              "type": "Identifier",
              "start": 215,
              "end": 221,
              "loc": {
                "start": {
                  "line": 10,
                  "column": 0
                },
                "end": {
                  "line": 10,
                  "column": 6
                },
                "identifierName": "module"
              },
              "name": "module"
            },
            "property": {
              "type": "Identifier",
              "start": 222,
              "end": 229,
              "loc": {
                "start": {
                  "line": 10,
                  "column": 7
                },
                "end": {
                  "line": 10,
                  "column": 14
                },
                "identifierName": "exports"
              },
              "name": "exports"
            },
            "computed": false
          },
          "right": {
            "type": "CallExpression",
            "start": 232,
            "end": 298,
            "loc": {
              "start": {
                "line": 10,
                "column": 17
              },
              "end": {
                "line": 10,
                "column": 83
              }
            },
            "callee": {
              "type": "MemberExpression",
              "start": 232,
              "end": 246,
              "loc": {
                "start": {
                  "line": 10,
                  "column": 17
                },
                "end": {
                  "line": 10,
                  "column": 31
                }
              },
              "object": {
                "type": "Identifier",
                "start": 232,
                "end": 240,
                "loc": {
                  "start": {
                    "line": 10,
                    "column": 17
                  },
                  "end": {
                    "line": 10,
                    "column": 25
                  },
                  "identifierName": "mongoose"
                },
                "name": "mongoose"
              },
              "property": {
                "type": "Identifier",
                "start": 241,
                "end": 246,
                "loc": {
                  "start": {
                    "line": 10,
                    "column": 26
                  },
                  "end": {
                    "line": 10,
                    "column": 31
                  },
                  "identifierName": "model"
                },
                "name": "model"
              },
              "computed": false
            },
            "arguments": [
              {
                "type": "StringLiteral",
                "start": 247,
                "end": 261,
                "loc": {
                  "start": {
                    "line": 10,
                    "column": 32
                  },
                  "end": {
                    "line": 10,
                    "column": 46
                  }
                },
                "extra": {
                  "rawValue": "EntradaSaida",
                  "raw": "'EntradaSaida'"
                },
                "value": "EntradaSaida"
              },
              {
                "type": "Identifier",
                "start": 263,
                "end": 281,
                "loc": {
                  "start": {
                    "line": 10,
                    "column": 48
                  },
                  "end": {
                    "line": 10,
                    "column": 66
                  },
                  "identifierName": "EntradaSaidaSchema"
                },
                "name": "EntradaSaidaSchema"
              },
              {
                "type": "StringLiteral",
                "start": 283,
                "end": 297,
                "loc": {
                  "start": {
                    "line": 10,
                    "column": 68
                  },
                  "end": {
                    "line": 10,
                    "column": 82
                  }
                },
                "extra": {
                  "rawValue": "EntradaSaida",
                  "raw": "'EntradaSaida'"
                },
                "value": "EntradaSaida"
              }
            ]
          }
        }
      }
    ],
    "directives": []
  },
  "comments": [
    {
      "type": "CommentLine",
      "value": "_id:{type:String},",
      "start": 89,
      "end": 109,
      "loc": {
        "start": {
          "line": 4,
          "column": 2
        },
        "end": {
          "line": 4,
          "column": 22
        }
      }
    }
  ],
  "tokens": [
    {
      "type": {
        "label": "var",
        "keyword": "var",
        "beforeExpr": false,
        "startsExpr": false,
        "rightAssociative": false,
        "isLoop": false,
        "isAssign": false,
        "prefix": false,
        "postfix": false,
        "binop": null,
        "updateContext": null
      },
      "value": "var",
      "start": 0,
      "end": 3,
      "loc": {
        "start": {
          "line": 1,
          "column": 0
        },
        "end": {
          "line": 1,
          "column": 3
        }
      }
    },
    {
      "type": {
        "label": "name",
        "beforeExpr": false,
        "startsExpr": true,
        "rightAssociative": false,
        "isLoop": false,
        "isAssign": false,
        "prefix": false,
        "postfix": false,
        "binop": null
      },
      "value": "mongoose",
      "start": 4,
      "end": 12,
      "loc": {
        "start": {
          "line": 1,
          "column": 4
        },
        "end": {
          "line": 1,
          "column": 12
        }
      }
    },
    {
      "type": {
        "label": "=",
        "beforeExpr": true,
        "startsExpr": false,
        "rightAssociative": false,
        "isLoop": false,
        "isAssign": true,
        "prefix": false,
        "postfix": false,
        "binop": null,
        "updateContext": null
      },
      "value": "=",
      "start": 13,
      "end": 14,
      "loc": {
        "start": {
          "line": 1,
          "column": 13
        },
        "end": {
          "line": 1,
          "column": 14
        }
      }
    },
    {
      "type": {
        "label": "name",
        "beforeExpr": false,
        "startsExpr": true,
        "rightAssociative": false,
        "isLoop": false,
        "isAssign": false,
        "prefix": false,
        "postfix": false,
        "binop": null
      },
      "value": "require",
      "start": 15,
      "end": 22,
      "loc": {
        "start": {
          "line": 1,
          "column": 15
        },
        "end": {
          "line": 1,
          "column": 22
        }
      }
    },
    {
      "type": {
        "label": "(",
        "beforeExpr": true,
        "startsExpr": true,
        "rightAssociative": false,
        "isLoop": false,
        "isAssign": false,
        "prefix": false,
        "postfix": false,
        "binop": null
      },
      "start": 22,
      "end": 23,
      "loc": {
        "start": {
          "line": 1,
          "column": 22
        },
        "end": {
          "line": 1,
          "column": 23
        }
      }
    },
    {
      "type": {
        "label": "string",
        "beforeExpr": false,
        "startsExpr": true,
        "rightAssociative": false,
        "isLoop": false,
        "isAssign": false,
        "prefix": false,
        "postfix": false,
        "binop": null,
        "updateContext": null
      },
      "value": "mongoose",
      "start": 23,
      "end": 33,
      "loc": {
        "start": {
          "line": 1,
          "column": 23
        },
        "end": {
          "line": 1,
          "column": 33
        }
      }
    },
    {
      "type": {
        "label": ")",
        "beforeExpr": false,
        "startsExpr": false,
        "rightAssociative": false,
        "isLoop": false,
        "isAssign": false,
        "prefix": false,
        "postfix": false,
        "binop": null
      },
      "start": 33,
      "end": 34,
      "loc": {
        "start": {
          "line": 1,
          "column": 33
        },
        "end": {
          "line": 1,
          "column": 34
        }
      }
    },
    {
      "type": {
        "label": ";",
        "beforeExpr": true,
        "startsExpr": false,
        "rightAssociative": false,
        "isLoop": false,
        "isAssign": false,
        "prefix": false,
        "postfix": false,
        "binop": null,
        "updateContext": null
      },
      "start": 34,
      "end": 35,
      "loc": {
        "start": {
          "line": 1,
          "column": 34
        },
        "end": {
          "line": 1,
          "column": 35
        }
      }
    },
    {
      "type": {
        "label": "var",
        "keyword": "var",
        "beforeExpr": false,
        "startsExpr": false,
        "rightAssociative": false,
        "isLoop": false,
        "isAssign": false,
        "prefix": false,
        "postfix": false,
        "binop": null,
        "updateContext": null
      },
      "value": "var",
      "start": 39,
      "end": 42,
      "loc": {
        "start": {
          "line": 3,
          "column": 0
        },
        "end": {
          "line": 3,
          "column": 3
        }
      }
    },
    {
      "type": {
        "label": "name",
        "beforeExpr": false,
        "startsExpr": true,
        "rightAssociative": false,
        "isLoop": false,
        "isAssign": false,
        "prefix": false,
        "postfix": false,
        "binop": null
      },
      "value": "EntradaSaidaSchema",
      "start": 43,
      "end": 61,
      "loc": {
        "start": {
          "line": 3,
          "column": 4
        },
        "end": {
          "line": 3,
          "column": 22
        }
      }
    },
    {
      "type": {
        "label": "=",
        "beforeExpr": true,
        "startsExpr": false,
        "rightAssociative": false,
        "isLoop": false,
        "isAssign": true,
        "prefix": false,
        "postfix": false,
        "binop": null,
        "updateContext": null
      },
      "value": "=",
      "start": 62,
      "end": 63,
      "loc": {
        "start": {
          "line": 3,
          "column": 23
        },
        "end": {
          "line": 3,
          "column": 24
        }
      }
    },
    {
      "type": {
        "label": "new",
        "keyword": "new",
        "beforeExpr": true,
        "startsExpr": true,
        "rightAssociative": false,
        "isLoop": false,
        "isAssign": false,
        "prefix": false,
        "postfix": false,
        "binop": null,
        "updateContext": null
      },
      "value": "new",
      "start": 64,
      "end": 67,
      "loc": {
        "start": {
          "line": 3,
          "column": 25
        },
        "end": {
          "line": 3,
          "column": 28
        }
      }
    },
    {
      "type": {
        "label": "name",
        "beforeExpr": false,
        "startsExpr": true,
        "rightAssociative": false,
        "isLoop": false,
        "isAssign": false,
        "prefix": false,
        "postfix": false,
        "binop": null
      },
      "value": "mongoose",
      "start": 68,
      "end": 76,
      "loc": {
        "start": {
          "line": 3,
          "column": 29
        },
        "end": {
          "line": 3,
          "column": 37
        }
      }
    },
    {
      "type": {
        "label": ".",
        "beforeExpr": false,
        "startsExpr": false,
        "rightAssociative": false,
        "isLoop": false,
        "isAssign": false,
        "prefix": false,
        "postfix": false,
        "binop": null,
        "updateContext": null
      },
      "start": 76,
      "end": 77,
      "loc": {
        "start": {
          "line": 3,
          "column": 37
        },
        "end": {
          "line": 3,
          "column": 38
        }
      }
    },
    {
      "type": {
        "label": "name",
        "beforeExpr": false,
        "startsExpr": true,
        "rightAssociative": false,
        "isLoop": false,
        "isAssign": false,
        "prefix": false,
        "postfix": false,
        "binop": null
      },
      "value": "Schema",
      "start": 77,
      "end": 83,
      "loc": {
        "start": {
          "line": 3,
          "column": 38
        },
        "end": {
          "line": 3,
          "column": 44
        }
      }
    },
    {
      "type": {
        "label": "(",
        "beforeExpr": true,
        "startsExpr": true,
        "rightAssociative": false,
        "isLoop": false,
        "isAssign": false,
        "prefix": false,
        "postfix": false,
        "binop": null
      },
      "start": 83,
      "end": 84,
      "loc": {
        "start": {
          "line": 3,
          "column": 44
        },
        "end": {
          "line": 3,
          "column": 45
        }
      }
    },
    {
      "type": {
        "label": "{",
        "beforeExpr": true,
        "startsExpr": true,
        "rightAssociative": false,
        "isLoop": false,
        "isAssign": false,
        "prefix": false,
        "postfix": false,
        "binop": null
      },
      "start": 84,
      "end": 85,
      "loc": {
        "start": {
          "line": 3,
          "column": 45
        },
        "end": {
          "line": 3,
          "column": 46
        }
      }
    },
    {
      "type": "CommentLine",
      "value": "_id:{type:String},",
      "start": 89,
      "end": 109,
      "loc": {
        "start": {
          "line": 4,
          "column": 2
        },
        "end": {
          "line": 4,
          "column": 22
        }
      }
    },
    {
      "type": {
        "label": "name",
        "beforeExpr": false,
        "startsExpr": true,
        "rightAssociative": false,
        "isLoop": false,
        "isAssign": false,
        "prefix": false,
        "postfix": false,
        "binop": null
      },
      "value": "_Nome",
      "start": 113,
      "end": 118,
      "loc": {
        "start": {
          "line": 5,
          "column": 2
        },
        "end": {
          "line": 5,
          "column": 7
        }
      }
    },
    {
      "type": {
        "label": ":",
        "beforeExpr": true,
        "startsExpr": false,
        "rightAssociative": false,
        "isLoop": false,
        "isAssign": false,
        "prefix": false,
        "postfix": false,
        "binop": null,
        "updateContext": null
      },
      "start": 118,
      "end": 119,
      "loc": {
        "start": {
          "line": 5,
          "column": 7
        },
        "end": {
          "line": 5,
          "column": 8
        }
      }
    },
    {
      "type": {
        "label": "{",
        "beforeExpr": true,
        "startsExpr": true,
        "rightAssociative": false,
        "isLoop": false,
        "isAssign": false,
        "prefix": false,
        "postfix": false,
        "binop": null
      },
      "start": 119,
      "end": 120,
      "loc": {
        "start": {
          "line": 5,
          "column": 8
        },
        "end": {
          "line": 5,
          "column": 9
        }
      }
    },
    {
      "type": {
        "label": "name",
        "beforeExpr": false,
        "startsExpr": true,
        "rightAssociative": false,
        "isLoop": false,
        "isAssign": false,
        "prefix": false,
        "postfix": false,
        "binop": null
      },
      "value": "type",
      "start": 120,
      "end": 124,
      "loc": {
        "start": {
          "line": 5,
          "column": 9
        },
        "end": {
          "line": 5,
          "column": 13
        }
      }
    },
    {
      "type": {
        "label": ":",
        "beforeExpr": true,
        "startsExpr": false,
        "rightAssociative": false,
        "isLoop": false,
        "isAssign": false,
        "prefix": false,
        "postfix": false,
        "binop": null,
        "updateContext": null
      },
      "start": 124,
      "end": 125,
      "loc": {
        "start": {
          "line": 5,
          "column": 13
        },
        "end": {
          "line": 5,
          "column": 14
        }
      }
    },
    {
      "type": {
        "label": "name",
        "beforeExpr": false,
        "startsExpr": true,
        "rightAssociative": false,
        "isLoop": false,
        "isAssign": false,
        "prefix": false,
        "postfix": false,
        "binop": null
      },
      "value": "String",
      "start": 125,
      "end": 131,
      "loc": {
        "start": {
          "line": 5,
          "column": 14
        },
        "end": {
          "line": 5,
          "column": 20
        }
      }
    },
    {
      "type": {
        "label": "}",
        "beforeExpr": false,
        "startsExpr": false,
        "rightAssociative": false,
        "isLoop": false,
        "isAssign": false,
        "prefix": false,
        "postfix": false,
        "binop": null
      },
      "start": 131,
      "end": 132,
      "loc": {
        "start": {
          "line": 5,
          "column": 20
        },
        "end": {
          "line": 5,
          "column": 21
        }
      }
    },
    {
      "type": {
        "label": ",",
        "beforeExpr": true,
        "startsExpr": false,
        "rightAssociative": false,
        "isLoop": false,
        "isAssign": false,
        "prefix": false,
        "postfix": false,
        "binop": null,
        "updateContext": null
      },
      "start": 132,
      "end": 133,
      "loc": {
        "start": {
          "line": 5,
          "column": 21
        },
        "end": {
          "line": 5,
          "column": 22
        }
      }
    },
    {
      "type": {
        "label": "name",
        "beforeExpr": false,
        "startsExpr": true,
        "rightAssociative": false,
        "isLoop": false,
        "isAssign": false,
        "prefix": false,
        "postfix": false,
        "binop": null
      },
      "value": "_EntradaSaida",
      "start": 137,
      "end": 150,
      "loc": {
        "start": {
          "line": 6,
          "column": 2
        },
        "end": {
          "line": 6,
          "column": 15
        }
      }
    },
    {
      "type": {
        "label": ":",
        "beforeExpr": true,
        "startsExpr": false,
        "rightAssociative": false,
        "isLoop": false,
        "isAssign": false,
        "prefix": false,
        "postfix": false,
        "binop": null,
        "updateContext": null
      },
      "start": 150,
      "end": 151,
      "loc": {
        "start": {
          "line": 6,
          "column": 15
        },
        "end": {
          "line": 6,
          "column": 16
        }
      }
    },
    {
      "type": {
        "label": "{",
        "beforeExpr": true,
        "startsExpr": true,
        "rightAssociative": false,
        "isLoop": false,
        "isAssign": false,
        "prefix": false,
        "postfix": false,
        "binop": null
      },
      "start": 151,
      "end": 152,
      "loc": {
        "start": {
          "line": 6,
          "column": 16
        },
        "end": {
          "line": 6,
          "column": 17
        }
      }
    },
    {
      "type": {
        "label": "name",
        "beforeExpr": false,
        "startsExpr": true,
        "rightAssociative": false,
        "isLoop": false,
        "isAssign": false,
        "prefix": false,
        "postfix": false,
        "binop": null
      },
      "value": "type",
      "start": 152,
      "end": 156,
      "loc": {
        "start": {
          "line": 6,
          "column": 17
        },
        "end": {
          "line": 6,
          "column": 21
        }
      }
    },
    {
      "type": {
        "label": ":",
        "beforeExpr": true,
        "startsExpr": false,
        "rightAssociative": false,
        "isLoop": false,
        "isAssign": false,
        "prefix": false,
        "postfix": false,
        "binop": null,
        "updateContext": null
      },
      "start": 156,
      "end": 157,
      "loc": {
        "start": {
          "line": 6,
          "column": 21
        },
        "end": {
          "line": 6,
          "column": 22
        }
      }
    },
    {
      "type": {
        "label": "name",
        "beforeExpr": false,
        "startsExpr": true,
        "rightAssociative": false,
        "isLoop": false,
        "isAssign": false,
        "prefix": false,
        "postfix": false,
        "binop": null
      },
      "value": "String",
      "start": 157,
      "end": 163,
      "loc": {
        "start": {
          "line": 6,
          "column": 22
        },
        "end": {
          "line": 6,
          "column": 28
        }
      }
    },
    {
      "type": {
        "label": "}",
        "beforeExpr": false,
        "startsExpr": false,
        "rightAssociative": false,
        "isLoop": false,
        "isAssign": false,
        "prefix": false,
        "postfix": false,
        "binop": null
      },
      "start": 163,
      "end": 164,
      "loc": {
        "start": {
          "line": 6,
          "column": 28
        },
        "end": {
          "line": 6,
          "column": 29
        }
      }
    },
    {
      "type": {
        "label": ",",
        "beforeExpr": true,
        "startsExpr": false,
        "rightAssociative": false,
        "isLoop": false,
        "isAssign": false,
        "prefix": false,
        "postfix": false,
        "binop": null,
        "updateContext": null
      },
      "start": 164,
      "end": 165,
      "loc": {
        "start": {
          "line": 6,
          "column": 29
        },
        "end": {
          "line": 6,
          "column": 30
        }
      }
    },
    {
      "type": {
        "label": "name",
        "beforeExpr": false,
        "startsExpr": true,
        "rightAssociative": false,
        "isLoop": false,
        "isAssign": false,
        "prefix": false,
        "postfix": false,
        "binop": null
      },
      "value": "_Hora",
      "start": 169,
      "end": 174,
      "loc": {
        "start": {
          "line": 7,
          "column": 2
        },
        "end": {
          "line": 7,
          "column": 7
        }
      }
    },
    {
      "type": {
        "label": ":",
        "beforeExpr": true,
        "startsExpr": false,
        "rightAssociative": false,
        "isLoop": false,
        "isAssign": false,
        "prefix": false,
        "postfix": false,
        "binop": null,
        "updateContext": null
      },
      "start": 174,
      "end": 175,
      "loc": {
        "start": {
          "line": 7,
          "column": 7
        },
        "end": {
          "line": 7,
          "column": 8
        }
      }
    },
    {
      "type": {
        "label": "{",
        "beforeExpr": true,
        "startsExpr": true,
        "rightAssociative": false,
        "isLoop": false,
        "isAssign": false,
        "prefix": false,
        "postfix": false,
        "binop": null
      },
      "start": 175,
      "end": 176,
      "loc": {
        "start": {
          "line": 7,
          "column": 8
        },
        "end": {
          "line": 7,
          "column": 9
        }
      }
    },
    {
      "type": {
        "label": "name",
        "beforeExpr": false,
        "startsExpr": true,
        "rightAssociative": false,
        "isLoop": false,
        "isAssign": false,
        "prefix": false,
        "postfix": false,
        "binop": null
      },
      "value": "type",
      "start": 176,
      "end": 180,
      "loc": {
        "start": {
          "line": 7,
          "column": 9
        },
        "end": {
          "line": 7,
          "column": 13
        }
      }
    },
    {
      "type": {
        "label": ":",
        "beforeExpr": true,
        "startsExpr": false,
        "rightAssociative": false,
        "isLoop": false,
        "isAssign": false,
        "prefix": false,
        "postfix": false,
        "binop": null,
        "updateContext": null
      },
      "start": 180,
      "end": 181,
      "loc": {
        "start": {
          "line": 7,
          "column": 13
        },
        "end": {
          "line": 7,
          "column": 14
        }
      }
    },
    {
      "type": {
        "label": "name",
        "beforeExpr": false,
        "startsExpr": true,
        "rightAssociative": false,
        "isLoop": false,
        "isAssign": false,
        "prefix": false,
        "postfix": false,
        "binop": null
      },
      "value": "Date",
      "start": 181,
      "end": 185,
      "loc": {
        "start": {
          "line": 7,
          "column": 14
        },
        "end": {
          "line": 7,
          "column": 18
        }
      }
    },
    {
      "type": {
        "label": "}",
        "beforeExpr": false,
        "startsExpr": false,
        "rightAssociative": false,
        "isLoop": false,
        "isAssign": false,
        "prefix": false,
        "postfix": false,
        "binop": null
      },
      "start": 185,
      "end": 186,
      "loc": {
        "start": {
          "line": 7,
          "column": 18
        },
        "end": {
          "line": 7,
          "column": 19
        }
      }
    },
    {
      "type": {
        "label": "}",
        "beforeExpr": false,
        "startsExpr": false,
        "rightAssociative": false,
        "isLoop": false,
        "isAssign": false,
        "prefix": false,
        "postfix": false,
        "binop": null
      },
      "start": 188,
      "end": 189,
      "loc": {
        "start": {
          "line": 8,
          "column": 0
        },
        "end": {
          "line": 8,
          "column": 1
        }
      }
    },
    {
      "type": {
        "label": ",",
        "beforeExpr": true,
        "startsExpr": false,
        "rightAssociative": false,
        "isLoop": false,
        "isAssign": false,
        "prefix": false,
        "postfix": false,
        "binop": null,
        "updateContext": null
      },
      "start": 189,
      "end": 190,
      "loc": {
        "start": {
          "line": 8,
          "column": 1
        },
        "end": {
          "line": 8,
          "column": 2
        }
      }
    },
    {
      "type": {
        "label": "{",
        "beforeExpr": true,
        "startsExpr": true,
        "rightAssociative": false,
        "isLoop": false,
        "isAssign": false,
        "prefix": false,
        "postfix": false,
        "binop": null
      },
      "start": 191,
      "end": 192,
      "loc": {
        "start": {
          "line": 8,
          "column": 3
        },
        "end": {
          "line": 8,
          "column": 4
        }
      }
    },
    {
      "type": {
        "label": "name",
        "beforeExpr": false,
        "startsExpr": true,
        "rightAssociative": false,
        "isLoop": false,
        "isAssign": false,
        "prefix": false,
        "postfix": false,
        "binop": null
      },
      "value": "timestamps",
      "start": 192,
      "end": 202,
      "loc": {
        "start": {
          "line": 8,
          "column": 4
        },
        "end": {
          "line": 8,
          "column": 14
        }
      }
    },
    {
      "type": {
        "label": ":",
        "beforeExpr": true,
        "startsExpr": false,
        "rightAssociative": false,
        "isLoop": false,
        "isAssign": false,
        "prefix": false,
        "postfix": false,
        "binop": null,
        "updateContext": null
      },
      "start": 202,
      "end": 203,
      "loc": {
        "start": {
          "line": 8,
          "column": 14
        },
        "end": {
          "line": 8,
          "column": 15
        }
      }
    },
    {
      "type": {
        "label": "true",
        "keyword": "true",
        "beforeExpr": false,
        "startsExpr": true,
        "rightAssociative": false,
        "isLoop": false,
        "isAssign": false,
        "prefix": false,
        "postfix": false,
        "binop": null,
        "updateContext": null
      },
      "value": "true",
      "start": 204,
      "end": 208,
      "loc": {
        "start": {
          "line": 8,
          "column": 16
        },
        "end": {
          "line": 8,
          "column": 20
        }
      }
    },
    {
      "type": {
        "label": "}",
        "beforeExpr": false,
        "startsExpr": false,
        "rightAssociative": false,
        "isLoop": false,
        "isAssign": false,
        "prefix": false,
        "postfix": false,
        "binop": null
      },
      "start": 208,
      "end": 209,
      "loc": {
        "start": {
          "line": 8,
          "column": 20
        },
        "end": {
          "line": 8,
          "column": 21
        }
      }
    },
    {
      "type": {
        "label": ")",
        "beforeExpr": false,
        "startsExpr": false,
        "rightAssociative": false,
        "isLoop": false,
        "isAssign": false,
        "prefix": false,
        "postfix": false,
        "binop": null
      },
      "start": 209,
      "end": 210,
      "loc": {
        "start": {
          "line": 8,
          "column": 21
        },
        "end": {
          "line": 8,
          "column": 22
        }
      }
    },
    {
      "type": {
        "label": ";",
        "beforeExpr": true,
        "startsExpr": false,
        "rightAssociative": false,
        "isLoop": false,
        "isAssign": false,
        "prefix": false,
        "postfix": false,
        "binop": null,
        "updateContext": null
      },
      "start": 210,
      "end": 211,
      "loc": {
        "start": {
          "line": 8,
          "column": 22
        },
        "end": {
          "line": 8,
          "column": 23
        }
      }
    },
    {
      "type": {
        "label": "name",
        "beforeExpr": false,
        "startsExpr": true,
        "rightAssociative": false,
        "isLoop": false,
        "isAssign": false,
        "prefix": false,
        "postfix": false,
        "binop": null
      },
      "value": "module",
      "start": 215,
      "end": 221,
      "loc": {
        "start": {
          "line": 10,
          "column": 0
        },
        "end": {
          "line": 10,
          "column": 6
        }
      }
    },
    {
      "type": {
        "label": ".",
        "beforeExpr": false,
        "startsExpr": false,
        "rightAssociative": false,
        "isLoop": false,
        "isAssign": false,
        "prefix": false,
        "postfix": false,
        "binop": null,
        "updateContext": null
      },
      "start": 221,
      "end": 222,
      "loc": {
        "start": {
          "line": 10,
          "column": 6
        },
        "end": {
          "line": 10,
          "column": 7
        }
      }
    },
    {
      "type": {
        "label": "name",
        "beforeExpr": false,
        "startsExpr": true,
        "rightAssociative": false,
        "isLoop": false,
        "isAssign": false,
        "prefix": false,
        "postfix": false,
        "binop": null
      },
      "value": "exports",
      "start": 222,
      "end": 229,
      "loc": {
        "start": {
          "line": 10,
          "column": 7
        },
        "end": {
          "line": 10,
          "column": 14
        }
      }
    },
    {
      "type": {
        "label": "=",
        "beforeExpr": true,
        "startsExpr": false,
        "rightAssociative": false,
        "isLoop": false,
        "isAssign": true,
        "prefix": false,
        "postfix": false,
        "binop": null,
        "updateContext": null
      },
      "value": "=",
      "start": 230,
      "end": 231,
      "loc": {
        "start": {
          "line": 10,
          "column": 15
        },
        "end": {
          "line": 10,
          "column": 16
        }
      }
    },
    {
      "type": {
        "label": "name",
        "beforeExpr": false,
        "startsExpr": true,
        "rightAssociative": false,
        "isLoop": false,
        "isAssign": false,
        "prefix": false,
        "postfix": false,
        "binop": null
      },
      "value": "mongoose",
      "start": 232,
      "end": 240,
      "loc": {
        "start": {
          "line": 10,
          "column": 17
        },
        "end": {
          "line": 10,
          "column": 25
        }
      }
    },
    {
      "type": {
        "label": ".",
        "beforeExpr": false,
        "startsExpr": false,
        "rightAssociative": false,
        "isLoop": false,
        "isAssign": false,
        "prefix": false,
        "postfix": false,
        "binop": null,
        "updateContext": null
      },
      "start": 240,
      "end": 241,
      "loc": {
        "start": {
          "line": 10,
          "column": 25
        },
        "end": {
          "line": 10,
          "column": 26
        }
      }
    },
    {
      "type": {
        "label": "name",
        "beforeExpr": false,
        "startsExpr": true,
        "rightAssociative": false,
        "isLoop": false,
        "isAssign": false,
        "prefix": false,
        "postfix": false,
        "binop": null
      },
      "value": "model",
      "start": 241,
      "end": 246,
      "loc": {
        "start": {
          "line": 10,
          "column": 26
        },
        "end": {
          "line": 10,
          "column": 31
        }
      }
    },
    {
      "type": {
        "label": "(",
        "beforeExpr": true,
        "startsExpr": true,
        "rightAssociative": false,
        "isLoop": false,
        "isAssign": false,
        "prefix": false,
        "postfix": false,
        "binop": null
      },
      "start": 246,
      "end": 247,
      "loc": {
        "start": {
          "line": 10,
          "column": 31
        },
        "end": {
          "line": 10,
          "column": 32
        }
      }
    },
    {
      "type": {
        "label": "string",
        "beforeExpr": false,
        "startsExpr": true,
        "rightAssociative": false,
        "isLoop": false,
        "isAssign": false,
        "prefix": false,
        "postfix": false,
        "binop": null,
        "updateContext": null
      },
      "value": "EntradaSaida",
      "start": 247,
      "end": 261,
      "loc": {
        "start": {
          "line": 10,
          "column": 32
        },
        "end": {
          "line": 10,
          "column": 46
        }
      }
    },
    {
      "type": {
        "label": ",",
        "beforeExpr": true,
        "startsExpr": false,
        "rightAssociative": false,
        "isLoop": false,
        "isAssign": false,
        "prefix": false,
        "postfix": false,
        "binop": null,
        "updateContext": null
      },
      "start": 261,
      "end": 262,
      "loc": {
        "start": {
          "line": 10,
          "column": 46
        },
        "end": {
          "line": 10,
          "column": 47
        }
      }
    },
    {
      "type": {
        "label": "name",
        "beforeExpr": false,
        "startsExpr": true,
        "rightAssociative": false,
        "isLoop": false,
        "isAssign": false,
        "prefix": false,
        "postfix": false,
        "binop": null
      },
      "value": "EntradaSaidaSchema",
      "start": 263,
      "end": 281,
      "loc": {
        "start": {
          "line": 10,
          "column": 48
        },
        "end": {
          "line": 10,
          "column": 66
        }
      }
    },
    {
      "type": {
        "label": ",",
        "beforeExpr": true,
        "startsExpr": false,
        "rightAssociative": false,
        "isLoop": false,
        "isAssign": false,
        "prefix": false,
        "postfix": false,
        "binop": null,
        "updateContext": null
      },
      "start": 281,
      "end": 282,
      "loc": {
        "start": {
          "line": 10,
          "column": 66
        },
        "end": {
          "line": 10,
          "column": 67
        }
      }
    },
    {
      "type": {
        "label": "string",
        "beforeExpr": false,
        "startsExpr": true,
        "rightAssociative": false,
        "isLoop": false,
        "isAssign": false,
        "prefix": false,
        "postfix": false,
        "binop": null,
        "updateContext": null
      },
      "value": "EntradaSaida",
      "start": 283,
      "end": 297,
      "loc": {
        "start": {
          "line": 10,
          "column": 68
        },
        "end": {
          "line": 10,
          "column": 82
        }
      }
    },
    {
      "type": {
        "label": ")",
        "beforeExpr": false,
        "startsExpr": false,
        "rightAssociative": false,
        "isLoop": false,
        "isAssign": false,
        "prefix": false,
        "postfix": false,
        "binop": null
      },
      "start": 297,
      "end": 298,
      "loc": {
        "start": {
          "line": 10,
          "column": 82
        },
        "end": {
          "line": 10,
          "column": 83
        }
      }
    },
    {
      "type": {
        "label": ";",
        "beforeExpr": true,
        "startsExpr": false,
        "rightAssociative": false,
        "isLoop": false,
        "isAssign": false,
        "prefix": false,
        "postfix": false,
        "binop": null,
        "updateContext": null
      },
      "start": 298,
      "end": 299,
      "loc": {
        "start": {
          "line": 10,
          "column": 83
        },
        "end": {
          "line": 10,
          "column": 84
        }
      }
    },
    {
      "type": {
        "label": "eof",
        "beforeExpr": false,
        "startsExpr": false,
        "rightAssociative": false,
        "isLoop": false,
        "isAssign": false,
        "prefix": false,
        "postfix": false,
        "binop": null,
        "updateContext": null
      },
      "start": 299,
      "end": 299,
      "loc": {
        "start": {
          "line": 10,
          "column": 84
        },
        "end": {
          "line": 10,
          "column": 84
        }
      }
    }
  ]
}